streusel/__init__.py
streusel/gaussian_cube.py
streusel/geometry_manipulation_functions.py
streusel/math_functions.py
streusel/process_functions.py
streusel/vasp_object.py
streusel-1.1.1.dist-info/METADATA
streusel-1.1.1.dist-info/WHEEL
streusel-1.1.1.dist-info/top_level.txt
streusel-1.1.1.dist-info/RECORD
