Metadata-Version: 2.1
Name: streusel
Version: 1.1.1
Requires-Dist: tqdm
Requires-Dist: numpy
Requires-Dist: pandas
Requires-Dist: ase
